CHANGELOG.md
hookers/__init__.py
hookers-1.1.0.dist-info/LICENSE
hookers-1.1.0.dist-info/WHEEL
hookers-1.1.0.dist-info/METADATA
hookers-1.1.0.dist-info/RECORD
