Metadata-Version: 2.1
Name: hookers
Version: 1.1.0
Summary: Python function call hookers
Home-page: https://github.com/linw1995/hookers
License: MIT
Author: 林玮 (Jade Lin)
Author-email: linw1995@icloud.com
Requires-Python: >=3.9,<4.0
Classifier: Development Status :: 1 - Planning
Classifier: Intended Audience :: Developers
Classifier: License :: OSI Approved :: MIT License
Classifier: Operating System :: MacOS :: MacOS X
Classifier: Operating System :: Microsoft :: Windows
Classifier: Operating System :: POSIX
Classifier: Programming Language :: Python
Classifier: Programming Language :: Python :: 3
Classifier: Programming Language :: Python :: 3.9
Project-URL: Bug Tracker, https://github.com/linw1995/hookers/issues
Project-URL: Repository, https://github.com/linw1995/hookers
